COPYING
README.rst
setup.py
apigatewaycl/__init__.py
apigatewaycl.egg-info/PKG-INFO
apigatewaycl.egg-info/SOURCES.txt
apigatewaycl.egg-info/dependency_links.txt
apigatewaycl.egg-info/requires.txt
apigatewaycl.egg-info/top_level.txt
apigatewaycl/api_client/__init__.py
apigatewaycl/api_client/sii/__init__.py
apigatewaycl/api_client/sii/actividades_economicas.py
apigatewaycl/api_client/sii/bhe.py
apigatewaycl/api_client/sii/bte.py
apigatewaycl/api_client/sii/contribuyentes.py
apigatewaycl/api_client/sii/dte.py
apigatewaycl/api_client/sii/indicadores.py
apigatewaycl/api_client/sii/misii.py
apigatewaycl/api_client/sii/portal_mipyme.py
apigatewaycl/api_client/sii/rcv.py