Metadata-Version: 2.1
Name: apigatewaycl
Version: 4.0.1
Summary: Cliente para realizar la integración con los servicios web de API Gateway desde Python.
Home-page: https://github.com/apigatewaycl/apigateway-api-client-python
Author: API Gateway
Author-email: dev@apigateway.cl
License: LGPL
Keywords: sii chile
Platform: UNKNOWN
Classifier: Development Status :: 5 - Production/Stable
Classifier: Intended Audience :: Developers
Classifier: Topic :: Software Development :: Build Tools
Classifier: License :: OSI Approved :: GNU Lesser General Public License v3 or later (LGPLv3+)
Classifier: Programming Language :: Python :: 3
License-File: COPYING
